{
  "type": 3,
  "data": {
    "source": 0,
    "texts": [],
    "attributes": [
      {
        "id": 813,
        "attributes": {
          "style": {
            "transform": "translate(-99.9998%, 0%) translate3d(0px, 0px, 0px)"
          }
        }
      },
      {
        "id": 810,
        "attributes": {
          "style": {
            "transform": "translate(-99.9998%, 0%) translate3d(0px, 0px, 0px)"
          }
        }
      },
      {
        "id": 807,
        "attributes": {
          "style": {
            "transform": "translate(-99.9998%, 0%) translate3d(0px, 0px, 0px)"
          }
        }
      },
      {
        "id": 804,
        "attributes": {
          "style": {
            "transform": "translate(-99.9998%, 0%) translate3d(0px, 0px, 0px)"
          }
        }
      },
      {
        "id": 801,
        "attributes": {
          "style": {
            "transform": "translate(-99.9998%, 0%) translate3d(0px, 0px, 0px)"
          }
        }
      },
      {
        "id": 798,
        "attributes": {
          "style": {
            "transform": "translate(-99.9998%, 0%) translate3d(0px, 0px, 0px)"
          }
        }
      },
      {
        "id": 794,
        "attributes": {
          "style": {
            "transform": "translate(-99.9998%, 0%) translate3d(0px, 0px, 0px)"
          }
        }
      },
      {
        "id": 789,
        "attributes": {
          "style": {
            "transform": "translate(-99.9998%, 0%) translate3d(0px, 0px, 0px)"
          }
        }
      },
      {
        "id": 786,
        "attributes": {
          "style": {
            "transform": "translate(-99.9998%, 0%) translate3d(0px, 0px, 0px)"
          }
        }
      },
      {
        "id": 782,
        "attributes": {
          "style": {
            "transform": "translate(-99.9998%, 0%) translate3d(0px, 0px, 0px)"
          }
        }
      },
      {
        "id": 816,
        "attributes": {
          "style": {
            "transform": "translate(0%, -59.9999%) translate3d(0px, 0px, 0px)"
          }
        }
      },
      {
        "id": 908,
        "attributes": {
          "style": {
            "opacity": "0.0529"
          }
        }
      },
      {
        "id": 864,
        "attributes": {
          "style": {
            "opacity": "0.0529"
          }
        }
      },
      {
        "id": 820,
        "attributes": {
          "style": {
            "opacity": "0.0529"
          }
        }
      },
      {
        "id": 776,
        "attributes": {
          "style": {
            "opacity": "0.0529"
          }
        }
      },
      {
        "id": 732,
        "attributes": {
          "style": {
            "opacity": "0.0529"
          }
        }
      },
      {
        "id": 697,
        "attributes": {
          "style": {
            "opacity": "0.0529"
          }
        }
      },
      {
        "id": 656,
        "attributes": {
          "style": {
            "opacity": "0.0529"
          }
        }
      },
      {
        "id": 417,
        "attributes": {
          "style": {
            "transform": "translate(5.2922%, 0%) translate3d(0px, 0px, 0px)"
          }
        }
      },
      {
        "id": 421,
        "attributes": {
          "style": {
            "transform": "translate(6.6677%, 0%) translate3d(0px, 0px, 0px)"
          }
        }
      },
      {
        "id": 424,
        "attributes": {
          "style": {
            "transform": "translate(8.4008%, 0%) translate3d(0px, 0px, 0px)"
          }
        }
      },
      {
        "id": 429,
        "attributes": {
          "style": {
            "transform": "translate(10.5843%, 0%) translate3d(0px, 0px, 0px)"
          }
        }
      },
      {
        "id": 433,
        "attributes": {
          "style": {
            "transform": "translate(13.3354%, 0%) translate3d(0px, 0px, 0px)"
          }
        }
      },
      {
        "id": 436,
        "attributes": {
          "style": {
            "transform": "translate(16.8016%, 0%) translate3d(0px, 0px, 0px)"
          }
        }
      },
      {
        "id": 439,
        "attributes": {
          "style": {
            "transform": "translate(21.1686%, 0%) translate3d(0px, 0px, 0px)"
          }
        }
      },
      {
        "id": 442,
        "attributes": {
          "style": {
            "transform": "translate(26.6708%, 0%) translate3d(0px, 0px, 0px)"
          }
        }
      },
      {
        "id": 445,
        "attributes": {
          "style": {
            "transform": "translate(33.6031%, 0%) translate3d(0px, 0px, 0px)"
          }
        }
      },
      {
        "id": 448,
        "attributes": {
          "style": {
            "transform": "translate(42.3373%, 0%) translate3d(0px, 0px, 0px)"
          }
        }
      },
      {
        "id": 410,
        "attributes": {
          "style": {
            "transform": "translate(0%, 5.2922%) translate3d(0px, 0px, 0px)",
            "opacity": "0.9471"
          }
        }
      },
      {
        "id": 451,
        "attributes": {
          "style": {
            "transform": "translate(0%, 5.2922%) translate3d(0px, 0px, 0px)",
            "opacity": "0.9471"
          }
        }
      },
      {
        "id": 456,
        "attributes": {
          "style": {
            "opacity": "0.9471",
            "transform": "translate(-1.5876%, 0%) translate3d(0px, 0px, 0px) scale(0.9947, 0.9947)"
          }
        }
      },
      {
        "id": 463,
        "attributes": {
          "style": {
            "opacity": "0.9471",
            "transform": "translate(1.5876%, 0%) translate3d(0px, 0px, 0px) scale(0.9947, 0.9947)"
          }
        }
      },
      {
        "id": 155,
        "attributes": {
          "style": {
            "transform": "translate3d(-0.0168px, -0.0013px, 0px)"
          }
        }
      },
      {
        "id": 150,
        "attributes": {
          "style": {
            "transform": "translate3d(0.1355px, -0.0588px, 0px)"
          }
        }
      },
      {
        "id": 145,
        "attributes": {
          "style": {
            "transform": "translate3d(0.1873px, 0.1108px, 0px) scale(1.0001, 1.0001)"
          }
        }
      },
      {
        "id": 140,
        "attributes": {
          "style": {
            "transform": "translate3d(-0.4628px, -0.1274px, 0px) scale(1.0002, 1.0002)"
          }
        }
      }
    ],
    "removes": [],
    "adds": []
  },
  "timestamp": 1724410278515
}