{
  "type": 3,
  "data": {
    "source": 0,
    "texts": [],
    "attributes": [
      {
        "id": 734,
        "attributes": {
          "style": {
            "transform": "translate3d(35.4094px, 0px, 0px)"
          }
        }
      },
      {
        "id": 772,
        "attributes": {
          "style": {
            "transform": "translate(0%, 14.5685%) translate3d(0px, 0px, 0px)",
            "opacity": "0.2918"
          }
        }
      },
      {
        "id": 132,
        "attributes": {
          "style": {
            "transform": "translate3d(0px, 0px, 0px) scale(0.6088, 0.6088)",
            "opacity": "0.2176"
          }
        }
      },
      {
        "id": 127,
        "attributes": {
          "style": {
            "transform": "translate3d(0px, 0px, 0px) scale(0.6292, 0.6292)",
            "opacity": "0.2583"
          }
        }
      },
      {
        "id": 122,
        "attributes": {
          "style": {
            "transform": "translate3d(0px, 0px, 0px) scale(0.6401, 0.6401)",
            "opacity": "0.2801"
          }
        }
      },
      {
        "id": 117,
        "attributes": {
          "style": {
            "transform": "translate3d(0px, 0px, 0px) scale(0.6459, 0.6459)",
            "opacity": "0.2918"
          }
        }
      },
      {
        "id": 778,
        "attributes": {
          "style": {
            "transform": "translate3d(44.6698px, 0px, 0px)"
          }
        }
      },
      {
        "id": 816,
        "attributes": {
          "style": {
            "transform": "translate(0%, 34.0628%) translate3d(0px, 0px, 0px)",
            "opacity": "0.1066"
          }
        }
      },
      {
        "id": 140,
        "attributes": {
          "style": {
            "transform": "translate3d(0px, 0px, 0px) scale(0.5533, 0.5533)",
            "opacity": "0.1066"
          }
        }
      }
    ],
    "removes": [],
    "adds": []
  },
  "timestamp": 1724410248485
}