{
  "type": 3,
  "data": {
    "source": 0,
    "texts": [],
    "attributes": [
      {
        "id": 690,
        "attributes": {
          "style": {
            "transform": "translate(-99.9981%, 0%) translate3d(0px, 0px, 0px)"
          }
        }
      },
      {
        "id": 687,
        "attributes": {
          "style": {
            "transform": "translate(-99.9981%, 0%) translate3d(0px, 0px, 0px)"
          }
        }
      },
      {
        "id": 684,
        "attributes": {
          "style": {
            "transform": "translate(-99.9981%, 0%) translate3d(0px, 0px, 0px)"
          }
        }
      },
      {
        "id": 681,
        "attributes": {
          "style": {
            "transform": "translate(-99.9981%, 0%) translate3d(0px, 0px, 0px)"
          }
        }
      },
      {
        "id": 677,
        "attributes": {
          "style": {
            "transform": "translate(-99.9981%, 0%) translate3d(0px, 0px, 0px)"
          }
        }
      },
      {
        "id": 672,
        "attributes": {
          "style": {
            "transform": "translate(-99.9981%, 0%) translate3d(0px, 0px, 0px)"
          }
        }
      },
      {
        "id": 669,
        "attributes": {
          "style": {
            "transform": "translate(-99.9981%, 0%) translate3d(0px, 0px, 0px)"
          }
        }
      },
      {
        "id": 666,
        "attributes": {
          "style": {
            "transform": "translate(-99.9981%, 0%) translate3d(0px, 0px, 0px)"
          }
        }
      },
      {
        "id": 662,
        "attributes": {
          "style": {
            "transform": "translate(-99.9981%, 0%) translate3d(0px, 0px, 0px)"
          }
        }
      },
      {
        "id": 693,
        "attributes": {
          "style": {
            "transform": "translate(0%, -59.9989%) translate3d(0px, 0px, 0px)",
            "opacity": "0"
          }
        }
      },
      {
        "id": 908,
        "attributes": {
          "style": {
            "opacity": "0.0619"
          }
        }
      },
      {
        "id": 864,
        "attributes": {
          "style": {
            "opacity": "0.0619"
          }
        }
      },
      {
        "id": 820,
        "attributes": {
          "style": {
            "opacity": "0.0619"
          }
        }
      },
      {
        "id": 776,
        "attributes": {
          "style": {
            "opacity": "0.0619"
          }
        }
      },
      {
        "id": 732,
        "attributes": {
          "style": {
            "opacity": "0.0619"
          }
        }
      },
      {
        "id": 697,
        "attributes": {
          "style": {
            "opacity": "0.0619"
          }
        }
      },
      {
        "id": 656,
        "attributes": {
          "style": {
            "opacity": "0.0619"
          }
        }
      },
      {
        "id": 242,
        "attributes": {
          "style": {
            "transform": "translate(6.1925%, 0%) translate3d(0px, 0px, 0px)"
          }
        }
      },
      {
        "id": 246,
        "attributes": {
          "style": {
            "transform": "translate(7.8021%, 0%) translate3d(0px, 0px, 0px)"
          }
        }
      },
      {
        "id": 249,
        "attributes": {
          "style": {
            "transform": "translate(9.83%, 0%) translate3d(0px, 0px, 0px)"
          }
        }
      },
      {
        "id": 252,
        "attributes": {
          "style": {
            "transform": "translate(12.385%, 0%) translate3d(0px, 0px, 0px)"
          }
        }
      },
      {
        "id": 257,
        "attributes": {
          "style": {
            "transform": "translate(15.6041%, 0%) translate3d(0px, 0px, 0px)"
          }
        }
      },
      {
        "id": 261,
        "attributes": {
          "style": {
            "transform": "translate(19.66%, 0%) translate3d(0px, 0px, 0px)"
          }
        }
      },
      {
        "id": 264,
        "attributes": {
          "style": {
            "transform": "translate(24.77%, 0%) translate3d(0px, 0px, 0px)"
          }
        }
      },
      {
        "id": 267,
        "attributes": {
          "style": {
            "transform": "translate(31.2083%, 0%) translate3d(0px, 0px, 0px)"
          }
        }
      },
      {
        "id": 270,
        "attributes": {
          "style": {
            "transform": "translate(39.3199%, 0%) translate3d(0px, 0px, 0px)"
          }
        }
      },
      {
        "id": 235,
        "attributes": {
          "style": {
            "transform": "translate(0%, 6.1925%) translate3d(0px, 0px, 0px)",
            "opacity": "0.9381"
          }
        }
      },
      {
        "id": 273,
        "attributes": {
          "style": {
            "transform": "translate(0%, 6.1925%) translate3d(0px, 0px, 0px)",
            "opacity": "0.9381"
          }
        }
      },
      {
        "id": 278,
        "attributes": {
          "style": {
            "opacity": "0.9381",
            "transform": "translate(-1.8578%, 0%) translate3d(0px, 0px, 0px) scale(0.9938, 0.9938)"
          }
        }
      },
      {
        "id": 286,
        "attributes": {
          "style": {
            "opacity": "0.9381",
            "transform": "translate(1.8578%, 0%) translate3d(0px, 0px, 0px) scale(0.9938, 0.9938)"
          }
        }
      },
      {
        "id": 86,
        "attributes": {
          "style": {
            "transform": "translate3d(-0.0472px, 0.0095px, 0px)"
          }
        }
      },
      {
        "id": 81,
        "attributes": {
          "style": {
            "transform": "translate3d(0.2872px, -0.008px, 0px)"
          }
        }
      },
      {
        "id": 76,
        "attributes": {
          "style": {
            "transform": "translate3d(0.1881px, -0.047px, 0px) scale(1.0001, 1.0001)"
          }
        }
      },
      {
        "id": 71,
        "attributes": {
          "style": {
            "transform": "translate3d(-0.7634px, -0.5055px, 0px) scale(1.0003, 1.0003)"
          }
        }
      }
    ],
    "removes": [],
    "adds": []
  },
  "timestamp": 1724410268394
}