{
  "type": 3,
  "data": {
    "source": 0,
    "texts": [],
    "attributes": [
      {
        "id": 734,
        "attributes": {
          "style": {
            "transform": "translate3d(3.4915px, 0px, 0px)"
          }
        }
      },
      {
        "id": 772,
        "attributes": {
          "style": {
            "transform": "translate(0%, 3.4915%) translate3d(0px, 0px, 0px)",
            "opacity": "0.9302"
          }
        }
      },
      {
        "id": 117,
        "attributes": {
          "style": {
            "transform": "translate3d(0px, 0px, 0px) scale(0.9651, 0.9651)",
            "opacity": "0.9302"
          }
        }
      },
      {
        "id": 122,
        "attributes": {
          "style": {
            "transform": "translate3d(0px, 0px, 0px) scale(0.9348, 0.9348)",
            "opacity": "0.8697"
          }
        }
      },
      {
        "id": 127,
        "attributes": {
          "style": {
            "transform": "translate3d(0px, 0px, 0px) scale(0.8784, 0.8784)",
            "opacity": "0.7568"
          }
        }
      },
      {
        "id": 132,
        "attributes": {
          "style": {
            "transform": "translate3d(0px, 0px, 0px) scale(0.7731, 0.7731)",
            "opacity": "0.5462"
          }
        }
      }
    ],
    "removes": [],
    "adds": []
  },
  "timestamp": 1724410248337
}