{
  "type": 3,
  "data": {
    "source": 0,
    "texts": [],
    "attributes": [
      {
        "id": 822,
        "attributes": {
          "style": {
            "transform": "translate3d(49.9963px, 0px, 0px)"
          }
        }
      },
      {
        "id": 860,
        "attributes": {
          "style": {
            "transform": "translate(0%, 19.9986%) translate3d(0px, 0px, 0px)",
            "opacity": "0.0001"
          }
        }
      },
      {
        "id": 178,
        "attributes": {
          "style": {
            "transform": "translate3d(0px, 0px, 0px) scale(0.5, 0.5)",
            "opacity": "0.0001"
          }
        }
      },
      {
        "id": 173,
        "attributes": {
          "style": {
            "transform": "translate3d(0px, 0px, 0px) scale(0.5, 0.5)",
            "opacity": "0.0001"
          }
        }
      },
      {
        "id": 168,
        "attributes": {
          "style": {
            "transform": "translate3d(0px, 0px, 0px) scale(0.5, 0.5)",
            "opacity": "0.0001"
          }
        }
      },
      {
        "id": 163,
        "attributes": {
          "style": {
            "transform": "translate3d(0px, 0px, 0px) scale(0.5, 0.5)",
            "opacity": "0.0001"
          }
        }
      },
      {
        "id": 866,
        "attributes": {
          "style": {
            "transform": "translate3d(1.1518px, 0px, 0px)"
          }
        }
      },
      {
        "id": 904,
        "attributes": {
          "style": {
            "transform": "translate(0%, 1.1518%) translate3d(0px, 0px, 0px)",
            "opacity": "0.977"
          }
        }
      },
      {
        "id": 186,
        "attributes": {
          "style": {
            "transform": "translate3d(0px, 0px, 0px) scale(0.9885, 0.9885)",
            "opacity": "0.977"
          }
        }
      },
      {
        "id": 191,
        "attributes": {
          "style": {
            "transform": "translate3d(0px, 0px, 0px) scale(0.9785, 0.9785)",
            "opacity": "0.957"
          }
        }
      },
      {
        "id": 196,
        "attributes": {
          "style": {
            "transform": "translate3d(0px, 0px, 0px) scale(0.9599, 0.9599)",
            "opacity": "0.9198"
          }
        }
      },
      {
        "id": 201,
        "attributes": {
          "style": {
            "transform": "translate3d(0px, 0px, 0px) scale(0.9252, 0.9252)",
            "opacity": "0.8503"
          }
        }
      }
    ],
    "removes": [],
    "adds": []
  },
  "timestamp": 1724587220574
}