{
  "type": 3,
  "data": {
    "source": 0,
    "texts": [],
    "attributes": [
      {
        "id": 778,
        "attributes": {
          "style": {
            "transform": "translate3d(31.2157px, 0px, 0px)"
          }
        }
      },
      {
        "id": 816,
        "attributes": {
          "style": {
            "transform": "translate(0%, 12.5113%) translate3d(0px, 0px, 0px)",
            "opacity": "0.3757"
          }
        }
      },
      {
        "id": 155,
        "attributes": {
          "style": {
            "transform": "translate3d(0px, 0px, 0px) scale(0.6855, 0.6855)",
            "opacity": "0.3711"
          }
        }
      },
      {
        "id": 150,
        "attributes": {
          "style": {
            "transform": "translate3d(0px, 0px, 0px) scale(0.6868, 0.6868)",
            "opacity": "0.3736"
          }
        }
      },
      {
        "id": 145,
        "attributes": {
          "style": {
            "transform": "translate3d(0px, 0px, 0px) scale(0.6875, 0.6875)",
            "opacity": "0.375"
          }
        }
      },
      {
        "id": 140,
        "attributes": {
          "style": {
            "transform": "translate3d(0px, 0px, 0px) scale(0.6878, 0.6878)",
            "opacity": "0.3757"
          }
        }
      },
      {
        "id": 734,
        "attributes": {
          "style": {
            "transform": "translate3d(20.3063px, 0px, 0px)"
          }
        }
      },
      {
        "id": 772,
        "attributes": {
          "style": {
            "transform": "translate(0%, 20.3063%) translate3d(0px, 0px, 0px)",
            "opacity": "0.5939"
          }
        }
      },
      {
        "id": 117,
        "attributes": {
          "style": {
            "transform": "translate3d(0px, 0px, 0px) scale(0.7969, 0.7969)",
            "opacity": "0.5939"
          }
        }
      },
      {
        "id": 122,
        "attributes": {
          "style": {
            "transform": "translate3d(0px, 0px, 0px) scale(0.6211, 0.6211)",
            "opacity": "0.2421"
          }
        }
      }
    ],
    "removes": [],
    "adds": []
  },
  "timestamp": 1724587219307
}